puentespablojosuecuadrado/__init__.py
puentespablojosuecuadrado/matemáticas.py
puentespablojosuecuadrado-0.1.0.dist-info/METADATA
puentespablojosuecuadrado-0.1.0.dist-info/WHEEL
puentespablojosuecuadrado-0.1.0.dist-info/RECORD
