Metadata-Version: 2.1
Name: puentespablojosuecuadrado
Version: 0.1.0
Summary: paquetedeprueba
Author: pablo cuadrado
Author-email: pjcuadrado@utpl.edu.ec
Requires-Python: >=3.10.0,<3.12
Classifier: Programming Language :: Python :: 3
Classifier: Programming Language :: Python :: 3.10
Classifier: Programming Language :: Python :: 3.11
